aoc/__init__.py
aoc/base.py
aoc/base_tests.py
aoc/input_providers.py
aoc/logger.py
aoc/main.py
aoc/py.typed
aoc/templates/day_template/__init__.py
aoc/templates/day_template/test_solution.py
aoc_python_cli-0.2.1.dist-info/LICENCE
aoc_python_cli-0.2.1.dist-info/METADATA
aoc_python_cli-0.2.1.dist-info/WHEEL
aoc_python_cli-0.2.1.dist-info/entry_points.txt
aoc_python_cli-0.2.1.dist-info/RECORD
