Metadata-Version: 2.1
Name: aoc-python-cli
Version: 0.2.1
Summary: Advent of Code Python scaffolding/running/submitting CLI
Home-page: https://nekeal.github.io/advent-of-code-python-cli
License: MIT
Author: nekeal
Author-email: szymon.sc.cader@gmail.com
Requires-Python: >=3.11,<4.0
Classifier: Intended Audience :: Developers
Classifier: License :: OSI Approved :: MIT License
Classifier: Operating System :: OS Independent
Classifier: Programming Language :: Python
Classifier: Programming Language :: Python :: 3
Classifier: Programming Language :: Python :: 3.11
Classifier: Programming Language :: Python :: 3.12
Classifier: Programming Language :: Python :: 3.13
Classifier: Topic :: Software Development :: Libraries :: Python Modules
Classifier: Typing :: Typed
Requires-Dist: advent-of-code-data (>=2.0.1,<3.0.0)
Requires-Dist: pytest
Requires-Dist: typer (>=0.9.0,<0.10.0)
Project-URL: Repository, https://github.com/nekeal/advent-of-code-python-cli
